models_extensions/__init__.py
models_extensions/admin.py
models_extensions/apps.py
models_extensions/models.py
models_extensions/migrations/__init__.py
tests/__init__.py
tests/test_models.py
django_extensions_models-1.0.dist-info/LICENSE
django_extensions_models-1.0.dist-info/METADATA
django_extensions_models-1.0.dist-info/WHEEL
django_extensions_models-1.0.dist-info/top_level.txt
django_extensions_models-1.0.dist-info/RECORD
