Metadata-Version: 2.1
Name: django-extensions-models
Version: 1.0
Summary: model extensions with timestamp and uuid and more
Home-page: https://github.com/thomas545/django-extensions-models
Author: Thomas Adel
Author-email: thomas.adel31@gmail.com
License: MIT
Keywords: django-models-extensions model-extensions django-extensions
Platform: UNKNOWN
Classifier: Programming Language :: Python :: 3
Classifier: Framework :: Django
Classifier: License :: OSI Approved :: MIT License
Classifier: Intended Audience :: Developers
Classifier: Operating System :: OS Independent
Classifier: Topic :: Software Development
Requires-Python: >=3.5
Requires-Dist: Django (>=2.0)
